Workbook

Sheet Start Here
B1: SavingsClub Net Worth Tracker
B2: Free wealth tracker with age benchmarks · savingsclub.com
B4: How to use this tracker
B5: 1. Open the 'Net Worth' tab and type your own numbers into the soft-yellow cells. Everything else calculates itself.
B6: 2. Open the 'Dashboard' tab to see your total, liquid, and investable net worth, your debt ratio, and how you compare to other Americans your age.
B7: 3. Each month, add one new row of numbers on the 'Monthly Tracker' tab and watch the trend. The trend matters far more than any single month.
B8: 4. The 'Age Benchmarks' tab holds the Federal Reserve reference data. You do not need to edit it.
B10: The one rule for editing
B11: Only the soft-yellow cells are meant to be typed in. Every white or colored cell is a formula. If you overwrite a formula, that number will stop updating.
B13: What the three net worth numbers mean
B14: Total net worth = everything you own minus everything you owe. The full picture, including home equity and cars.
B15: Liquid net worth = cash and investments you could reach in an emergency, minus short-term debts. Excludes your home.
... B21: Free to keep and to share. Made by SavingsClub · savingsclub.com

Sheet Net Worth
B1: Your Net Worth
B2: Type your numbers into the yellow cells. Totals update automatically.
B4: ASSETS (What You Own) | C4: Amount
B5: Cash & Checking | C5: 5000
B6: Savings Accounts | C6: 15000
B7: Investment Accounts | C7: 35000
B8: Retirement (401k, IRA) | C8: 65000
B9: Home Value | C9: 350000
B10: Vehicle Value | C10: 18000
B11: Other Assets | C11: 5000
B12: Total Assets | C12: =SUM(C5:C11) -> 493000
B14: LIABILITIES (What You Owe) | C14: Amount
B15: Mortgage Balance | C15: 280000
B16: Home Equity Loan | C16: 0
B17: Student Loans | C17: 22000
B18: Car Loans | C18: 12000
B19: Credit Card Debt | C19: 3500
B20: Personal Loans | C20: 0
B21: Medical Debt | C21: 0
B22: Other Liabilities | C22: 0
B23: Total Liabilities | C23: =SUM(C15:C22) -> 317500
B25: YOUR NET WORTH | C25: =C12-C23 -> 175500
B26: Liquid Net Worth | C26: =(C5+C6+C7)-(C19+C20+C21+C22) -> 51500 | E26: Cash + investments you can reach fast, minus short-term debts
B27: Investable Net Worth | C27: =C5+C6+C7 -> 55000 | E27: Cash + investment accounts only
B28: Debt-to-Asset Ratio | C28: =IFERROR(C23/C12,0) -> 0.64401623 | E28: Under 50% is healthy. Higher means debt is dragging your net worth.
B30: Your Age | C30: 35 | E30: Used for the age benchmark comparison on the Dashboard
B31: Annual Pre-Tax Income | C31: 70000 | E31: Used for your 'on track' target (age x income / 10)
B33: Yellow cells = type here. White / colored cells = auto-calculated.

Sheet Age Benchmarks
B1: Net Worth by Age (Federal Reserve, 2022 SCF)
B4: Age Band | C4: Lower age | D4: Median | E4: Average
B5: Under 35 | C5: 0 | D5: 39000 | E5: 183500
B6: 35 to 44 | C6: 35 | D6: 135600 | E6: 549600
B7: 45 to 54 | C7: 45 | D7: 247200 | E7: 975800
B8: 55 to 64 | C8: 55 | D8: 364500 | E8: 1566900
B9: 65 to 74 | C9: 65 | D9: 410000 | E9: 1794600
B10: 75 and up | C10: 75 | D10: 334700 | E10: 1624100
B12: Source: Federal Reserve Survey of Consumer Finances, 2022 (2022 dollars). Latest completed survey; 2025 results expected late 2026.

Sheet Dashboard
B1: Your Financial Dashboard
B2: Updates from the numbers you enter on the 'Net Worth' tab
B4: TOTAL NET WORTH
B5: ='Net Worth'!C25 -> 175500
B7: LIQUID NET WORTH | D7: INVESTABLE | F7: DEBT RATIO
B8: ='Net Worth'!C26 -> 51500 | D8: ='Net Worth'!C27 -> 55000 | F8: ='Net Worth'!C28 -> 0.64401623
B10: Total Assets | C10: ='Net Worth'!C12 -> 493000
B11: Total Liabilities | C11: ='Net Worth'!C23 -> 317500
B13: How you compare for your age
B14: Your age | C14: ='Net Worth'!C30 -> 35
B15: Median for your age | C15: =IF(ISNUMBER('Net Worth'!C30),INDEX('Age Benchmarks'!$D$5:$D$10,IFERROR(MATCH('Net Worth'!C30,'Age Benchmarks'!$C$5:$C$10,1),1)),0) -> 135600
B16: You vs median | C16: ='Net Worth'!C25-C15 -> 39900
B17: =IF(C16>=5000,"Ahead of the typical household your age.",IF(C16<=-5000,"Below the median for your age - see the strategies on savingsclub.com.","Right around the median for your age.")) -> Ahead of the typical household your age.
B19: 'On track' target | C19: =IFERROR('Net Worth'!C30*'Net Worth'!C31/10,0) -> 245000 | E19: (Millionaire Next Door: age x income / 10)

Sheet Monthly Tracker
B1: Monthly Net Worth Tracker
B2: Row 1 links to your current numbers. Each month, fill the next row's yellow cells.
B4: Month | C4: Total Assets | D4: Total Liabilities | E4: Net Worth | F4: Change
B5: Month 1 (now) | C5: ='Net Worth'!C12 -> 493000 | D5: ='Net Worth'!C23 -> 317500 | E5: =IF(C5="","",C5-D5) -> 175500
B6: Month 2 | E6: =IF(C6="","",C6-D6) | F6: =IF(OR(E6="",E5=""),"",E6-E5)
B7: Month 3 | E7: =IF(C7="","",C7-D7) | F7: =IF(OR(E7="",E6=""),"",E7-E6)
B8: Month 4 | E8: =IF(C8="","",C8-D8) | F8: =IF(OR(E8="",E7=""),"",E8-E7)
B9: Month 5 | E9: =IF(C9="","",C9-D9) | F9: =IF(OR(E9="",E8=""),"",E9-E8)
B10: Month 6 | E10: =IF(C10="","",C10-D10) | F10: =IF(OR(E10="",E9=""),"",E10-E9)
B11: Month 7 | E11: =IF(C11="","",C11-D11) | F11: =IF(OR(E11="",E10=""),"",E11-E10)
B12: Month 8 | E12: =IF(C12="","",C12-D12) | F12: =IF(OR(E12="",E11=""),"",E12-E11)
B13: Month 9 | E13: =IF(C13="","",C13-D13) | F13: =IF(OR(E13="",E12=""),"",E13-E12)
B14: Month 10 | E14: =IF(C14="","",C14-D14) | F14: =IF(OR(E14="",E13=""),"",E14-E13)
B15: Month 11 | E15: =IF(C15="","",C15-D15) | F15: =IF(OR(E15="",E14=""),"",E15-E14)
B16: Month 12 | E16: =IF(C16="","",C16-D16) | F16: =IF(OR(E16="",E15=""),"",E16-E15)
